Python_Proxy/Buffer.py
Python_Proxy/GenerateCertificates.py
Python_Proxy/Proxy.py
Python_Proxy/TcpProxy.py
Python_Proxy/TcpSslProxy.py
Python_Proxy/UdpProxy.py
Python_Proxy/__init__.py
Python_Proxy-0.0.1.dist-info/LICENSE
Python_Proxy-0.0.1.dist-info/METADATA
Python_Proxy-0.0.1.dist-info/WHEEL
Python_Proxy-0.0.1.dist-info/top_level.txt
Python_Proxy-0.0.1.dist-info/RECORD
