Metadata-Version: 2.1
Name: Python-Proxy
Version: 0.0.1
Summary: Multi Purpose UDP, TCP, TCP/SSL Proxy for python
Home-page: https://github.com/tomorroisnew/Python-Proxy
Author: tomorrowisnew
Author-email: tomorrowisnew <roldanbrandon62@gmail.com>
License: MIT
Classifier: Programming Language :: Python :: 3
Classifier: License :: OSI Approved :: MIT License
Classifier: Operating System :: OS Independent
Requires-Python: >=3.7
License-File: LICENSE
Requires-Dist: setuptools (>=61.0)
Requires-Dist: loguru
Requires-Dist: pyOpenSSL
